wNMF/__init__.py
wNMF/wNMF.py
wNMF-0.0.42.dist-info/LICENSE
wNMF-0.0.42.dist-info/METADATA
wNMF-0.0.42.dist-info/WHEEL
wNMF-0.0.42.dist-info/top_level.txt
wNMF-0.0.42.dist-info/RECORD
