Metadata-Version: 2.1
Name: wNMF
Version: 0.0.42
Summary: wNMF: weighted Non-Negative matrix Factorization
Home-page: https://github.com/asn32/weighted-nmf
Author: SN
Author-email: scottnanda@gmail.com
License: MIT License
Platform: UNKNOWN
Classifier: Programming Language :: Python
Classifier: Programming Language :: Python :: 3
Classifier: Programming Language :: Python :: 3.6
Classifier: Topic :: Scientific/Engineering :: Bio-Informatics
Classifier: Topic :: Scientific/Engineering :: Mathematics
Requires-Python: >=3.6
License-File: LICENSE
Requires-Dist: numpy (>=1.13)
